acb_mse.py
acb_mse-1.0.6.dist-info/METADATA
acb_mse-1.0.6.dist-info/WHEEL
acb_mse-1.0.6.dist-info/licenses/LICENSE
acb_mse-1.0.6.dist-info/RECORD
