Metadata-Version: 2.1
Name: acb_mse
Version: 1.0.6
Summary: Automatic-Class-Balanced MSE Loss for PyTorch (ACB-MSE) to combat class imbalanced datasets and stabilise fluctuating loss gradients.
Project-URL: Homepage, https://github.com/Adillwma/ACB-MSE
Project-URL: Bug Tracker, https://github.com/Adillwma/ACB-MSE/issues
Author-email: Adill Al-Ashgar <adillwmaa@gmail.com>
License-File: LICENSE
Classifier: License :: OSI Approved :: MIT License
Classifier: Operating System :: OS Independent
Classifier: Programming Language :: Python :: 3
Requires-Python: >=3.7
Requires-Dist: torch>=2.0.0
